sphinx_needs/__init__.py
sphinx_needs/builder.py
sphinx_needs/config.py
sphinx_needs/data.py
sphinx_needs/debug.py
sphinx_needs/defaults.py
sphinx_needs/diagrams_common.py
sphinx_needs/environment.py
sphinx_needs/errors.py
sphinx_needs/exceptions.py
sphinx_needs/external_needs.py
sphinx_needs/filter_common.py
sphinx_needs/layout.py
sphinx_needs/logging.py
sphinx_needs/need_constraints.py
sphinx_needs/need_item.py
sphinx_needs/needs.py
sphinx_needs/needs_schema.py
sphinx_needs/needsfile.json
sphinx_needs/needsfile.py
sphinx_needs/utils.py
sphinx_needs/variants.py
sphinx_needs/views.py
sphinx_needs/warnings.py
sphinx_needs/api/__init__.py
sphinx_needs/api/configuration.py
sphinx_needs/api/exceptions.py
sphinx_needs/api/need.py
sphinx_needs/css/common/need_core.css
sphinx_needs/css/common/need_links.css
sphinx_needs/css/common/need_style.css
sphinx_needs/css/common/need_toggle.css
sphinx_needs/css/common/needstable.css
sphinx_needs/css/themes/blank.css
sphinx_needs/css/themes/dark.css
sphinx_needs/css/themes/modern.css
sphinx_needs/directives/__init__.py
sphinx_needs/directives/list2need.py
sphinx_needs/directives/need.py
sphinx_needs/directives/needbar.py
sphinx_needs/directives/needextend.py
sphinx_needs/directives/needextract.py
sphinx_needs/directives/needgantt.py
sphinx_needs/directives/needimport.py
sphinx_needs/directives/needimport_template.rst
sphinx_needs/directives/needlist.py
sphinx_needs/directives/needpie.py
sphinx_needs/directives/needreport.py
sphinx_needs/directives/needreport_template.rst
sphinx_needs/directives/needsequence.py
sphinx_needs/directives/needservice.py
sphinx_needs/directives/needtable.py
sphinx_needs/directives/needuml.py
sphinx_needs/directives/utils.py
sphinx_needs/directives/needflow/__init__.py
sphinx_needs/directives/needflow/_directive.py
sphinx_needs/directives/needflow/_graphviz.py
sphinx_needs/directives/needflow/_plantuml.py
sphinx_needs/directives/needflow/_shared.py
sphinx_needs/functions/__init__.py
sphinx_needs-6.3.0.dist-info/licenses/LICENSE
sphinx_needs-6.3.0.dist-info/WHEEL
sphinx_needs-6.3.0.dist-info/METADATA
sphinx_needs-6.3.0.dist-info/RECORD
