Metadata-Version: 2.4
Name: sphinx-needs
Version: 6.3.0
Summary: Sphinx needs extension for managing needs/requirements and specifications
Author-email: team useblocks <info@useblocks.com>
Requires-Python: >=3.10,<4
Classifier: Development Status :: 5 - Production/Stable
Classifier: Intended Audience :: Developers
Classifier: License :: OSI Approved :: MIT License
Classifier: Operating System :: OS Independent
Classifier: Programming Language :: Python
Classifier: Programming Language :: Python :: 3
Classifier: Programming Language :: Python :: 3.10
Classifier: Programming Language :: Python :: 3.11
Classifier: Programming Language :: Python :: 3.12
Classifier: Programming Language :: Python :: 3.13
Classifier: Programming Language :: Python :: 3.14
Classifier: Topic :: Documentation
Classifier: Topic :: Utilities
Classifier: Framework :: Sphinx :: Extension
License-File: LICENSE
Requires-Dist: sphinx>=7.4,<9
Requires-Dist: requests-file~=2.1
Requires-Dist: requests~=2.32
Requires-Dist: jsonschema-rs~=0.37.1
Requires-Dist: sphinx-data-viewer~=0.1.5
Requires-Dist: sphinxcontrib-jquery~=4.0
Requires-Dist: tomli; python_version < '3.11'
Requires-Dist: typing-extensions>=4.14.0
Requires-Dist: pytest-benchmark~=5.0 ; extra == "benchmark" and ( sys_platform != 'win32')
Requires-Dist: memray>=1.3.1,<2.0.0 ; extra == "benchmark" and ( sys_platform != 'win32')
Requires-Dist: matplotlib>=3.3.0 ; extra == "docs"
Requires-Dist: sphinxcontrib-plantuml~=0.0 ; extra == "docs"
Requires-Dist: sphinx-copybutton~=0.5 ; extra == "docs"
Requires-Dist: sphinxcontrib-programoutput~=0.17 ; extra == "docs"
Requires-Dist: sphinx-design~=0.6 ; extra == "docs"
Requires-Dist: matplotlib>=3.3.0 ; extra == "plotting"
Requires-Dist: defusedxml~=0.7.1 ; extra == "test"
Requires-Dist: matplotlib>=3.3.0 ; extra == "test"
Requires-Dist: pytest~=8.0 ; extra == "test"
Requires-Dist: pytest-cov~=6.0 ; extra == "test"
Requires-Dist: syrupy~=4.0 ; extra == "test"
Requires-Dist: sphinxcontrib-plantuml~=0.0 ; extra == "test"
Requires-Dist: lxml~=6.0 ; extra == "test"
Requires-Dist: responses~=0.22.0 ; extra == "test"
Requires-Dist: pydantic~=2.12 ; extra == "test"
Requires-Dist: pytest-xprocess~=1.0 ; extra == "test"
Requires-Dist: pyyaml ~= 6.0 ; extra == "test"
Requires-Dist: pytest-xdist ; extra == "test-parallel"
Requires-Dist: furo~=2024.8.6 ; extra == "theme-furo"
Requires-Dist: sphinx-immaterial~=0.11.11 ; extra == "theme-im"
Requires-Dist: pydata-sphinx-theme~=0.15.2 ; extra == "theme-pds"
Requires-Dist: sphinx_rtd_theme>=3.0.2,<4 ; extra == "theme-rtd"
Project-URL: Documentation, https://sphinx-needs.readthedocs.io/en/latest/
Project-URL: Repository, http://github.com/useblocks/sphinx-needs
Provides-Extra: benchmark
Provides-Extra: docs
Provides-Extra: plotting
Provides-Extra: test
Provides-Extra: test-parallel
Provides-Extra: theme-furo
Provides-Extra: theme-im
Provides-Extra: theme-pds
Provides-Extra: theme-rtd
